CryptoClient/__init__.py
CryptoClient/__main__.py
CryptoLibrary/Plugin.py
CryptoLibrary/__init__.py
CryptoLibrary/__main__.py
CryptoLibrary/utils/__init__.py
CryptoLibrary/utils/cryptoutility.py
robotframework_crypto-0.4.2.dist-info/LICENSE
robotframework_crypto-0.4.2.dist-info/METADATA
robotframework_crypto-0.4.2.dist-info/WHEEL
robotframework_crypto-0.4.2.dist-info/entry_points.txt
robotframework_crypto-0.4.2.dist-info/top_level.txt
robotframework_crypto-0.4.2.dist-info/RECORD
