Metadata-Version: 2.1
Name: robotframework-crypto
Version: 0.4.2
Summary: A library for secure password handling.
Home-page: https://github.com/Snooz82/robotframework-crypto
Author: René Rohner(Snooz82)
Author-email: snooz@posteo.de
Classifier: Programming Language :: Python :: 3
Classifier: Programming Language :: Python :: 3.9
Classifier: Programming Language :: Python :: 3.10
Classifier: Programming Language :: Python :: 3.11
Classifier: Programming Language :: Python :: 3.12
Classifier: License :: OSI Approved :: Apache Software License
Classifier: Operating System :: OS Independent
Classifier: Topic :: Software Development :: Testing
Classifier: Topic :: Software Development :: Testing :: Acceptance
Classifier: Framework :: Robot Framework
Requires-Python: >=3.9
License-File: LICENSE
Requires-Dist: robotframework >=6.0.0
Requires-Dist: PyNaCl >=1.5.0
Requires-Dist: questionary >=2.0.1
